[
  {
    "year": "1960",
    "gdp": 102659854538.272
  },
  {
    "year": "1961",
    "gdp": 106481616605.737
  },
  {
    "year": "1962",
    "gdp": 109602728804.66
  },
  {
    "year": "1963",
    "gdp": 116172703554.942
  },
  {
    "year": "1964",
    "gdp": 124830997206.313
  },
  {
    "year": "1965",
    "gdp": 121540739092.467
  },
  {
    "year": "1966",
    "gdp": 121473492096.38
  },
  {
    "year": "1967",
    "gdp": 130979962681.358
  },
  {
    "year": "1968",
    "gdp": 135417471050.506
  },
  {
    "year": "1969",
    "gdp": 144273367807.11
  },
  {
    "year": "1970",
    "gdp": 151713876832.822
  },
  {
    "year": "1971",
    "gdp": 154206430210.978
  },
  {
    "year": "1972",
    "gdp": 153353204008.326
  },
  {
    "year": "1973",
    "gdp": 158406991259.221
  },
  {
    "year": "1974",
    "gdp": 160284646765.532
  },
  {
    "year": "1975",
    "gdp": 174950550917.23
  },
  {
    "year": "1976",
    "gdp": 177860159892.092
  },
  {
    "year": "1977",
    "gdp": 190763495784.221
  },
  {
    "year": "1978",
    "gdp": 201660921695.359
  },
  {
    "year": "1979",
    "gdp": 191097554176.085
  },
  {
    "year": "1980",
    "gdp": 203969544371.276
  },
  {
    "year": "1981",
    "gdp": 216220370534.94
  },
  {
    "year": "1982",
    "gdp": 223735613826.109
  },
  {
    "year": "1983",
    "gdp": 240043463101.412
  },
  {
    "year": "1984",
    "gdp": 249214894564.895
  },
  {
    "year": "1985",
    "gdp": 262309390835.691
  },
  {
    "year": "1986",
    "gdp": 274838767214.744
  },
  {
    "year": "1987",
    "gdp": 285737101754.917
  },
  {
    "year": "1988",
    "gdp": 313247249631.17
  },
  {
    "year": "1989",
    "gdp": 331877139034.054
  },
  {
    "year": "1990",
    "gdp": 350241409728.75
  },
  {
    "year": "1991",
    "gdp": 353942871036.377
  },
  {
    "year": "1992",
    "gdp": 373347420918.608
  },
  {
    "year": "1993",
    "gdp": 391084321407.043
  },
  {
    "year": "1994",
    "gdp": 417126329408.543
  },
  {
    "year": "1995",
    "gdp": 448721529195.152
  },
  {
    "year": "1996",
    "gdp": 482597860875.291
  },
  {
    "year": "1997",
    "gdp": 502142209662.26
  },
  {
    "year": "1998",
    "gdp": 533196771919.494
  },
  {
    "year": "1999",
    "gdp": 580362055023.189
  },
  {
    "year": "2000",
    "gdp": 602653710234.802
  },
  {
    "year": "2001",
    "gdp": 631725521906.089
  },
  {
    "year": "2002",
    "gdp": 655756204857.206
  },
  {
    "year": "2003",
    "gdp": 707301144107.221
  },
  {
    "year": "2004",
    "gdp": 763340165418.5
  },
  {
    "year": "2005",
    "gdp": 834215013605.932
  },
  {
    "year": "2006",
    "gdp": 911496398479.641
  },
  {
    "year": "2007",
    "gdp": 1000835444951.64
  },
  {
    "year": "2008",
    "gdp": 1039777522381.04
  },
  {
    "year": "2009",
    "gdp": 1127948437617.46
  },
  {
    "year": "2010",
    "gdp": 1243675529852.21
  },
  {
    "year": "2011",
    "gdp": 1326235036155.02
  },
  {
    "year": "2012",
    "gdp": 1393626581006.54
  },
  {
    "year": "2013",
    "gdp": 1489775906250.47
  },
  {
    "year": "2014",
    "gdp": 1600268265249.33
  }
]